{"skeleton":{"hash":"Yw4CWD0CdWPMeF9VyTeF5D6gW6M","spine":"3.8.99","images":"./tu/","audio":"D:/工作/武侠/特效/界面特效/八荒探秘/战斗"},"bones":[{"name":"root"},{"name":"bone4","parent":"root"},{"name":"bone5","parent":"bone4","scaleX":0.85,"scaleY":0.85}],"slots":[{"name":"hit1/hit1_00","bone":"bone5"}],"skins":[{"name":"default","attachments":{"hit1/hit1_00":{"hit1/hit1_00":{"width":450,"height":450},"hit1/hit1_01":{"width":450,"height":450},"hit1/hit1_02":{"width":450,"height":450},"hit1/hit1_04":{"width":450,"height":450},"hit1/hit1_10":{"width":450,"height":450},"hit1/hit1_12":{"width":450,"height":450},"hit1/hit1_14":{"width":450,"height":450},"hit1/hit1_16":{"width":450,"height":450},"hit1/hit1_18":{"width":450,"height":450}}}}],"events":{"hit":{}},"animations":{"Stand":{"slots":{"hit1/hit1_00":{"attachment":[{"name":"hit1/hit1_00"},{"time":0.0667,"name":"hit1/hit1_01"},{"time":0.1333,"name":"hit1/hit1_02"},{"time":0.2,"name":"hit1/hit1_04"},{"time":0.2667,"name":"hit1/hit1_10"},{"time":0.3333,"name":"hit1/hit1_12"},{"time":0.4,"name":"hit1/hit1_14"},{"time":0.4667,"name":"hit1/hit1_16"},{"time":0.5333,"name":"hit1/hit1_18"}]}},"events":[{"time":0.0667,"name":"hit","string":"hit"}]},"Stand2":{"slots":{"hit1/hit1_00":{"color":[{"color":"ee1717ff"}],"attachment":[{"name":"hit1/hit1_00"},{"time":0.0667,"name":"hit1/hit1_01"},{"time":0.1333,"name":"hit1/hit1_02"},{"time":0.2,"name":"hit1/hit1_04"},{"time":0.2667,"name":"hit1/hit1_10"},{"time":0.3333,"name":"hit1/hit1_12"},{"time":0.4,"name":"hit1/hit1_14"},{"time":0.4667,"name":"hit1/hit1_16"},{"time":0.5333,"name":"hit1/hit1_18"}]}},"events":[{"time":0.0667,"name":"hit","string":"hit"}]}}}